{
  "schema_version": 1,
  "name": "Blog Heart Beat",
  "repository": "Banhang-Chogao/zola",
  "generated_at": "2026-06-25T00:55:08.569312+00:00",
  "summary": {
    "in_progress": 6,
    "queued": 0,
    "success": 16,
    "failure": 3
  },
  "pull_requests": [],
  "runs": [
    {
      "id": 28139565156,
      "title": "fix(links): clear 10 internal 404s for green build-smoke (#884)",
      "workflow": "Slack Commit Notification",
      "branch": "main",
      "sha": "7b96ef1",
      "event": "push",
      "status": "in_progress",
      "conclusion": "",
      "created_at": "2026-06-25T00:54:59Z",
      "updated_at": "2026-06-25T00:55:03Z",
      "url": "https://github.com/Banhang-Chogao/zola/actions/runs/28139565156"
    },
    {
      "id": 28139565154,
      "title": "fix(links): clear 10 internal 404s for green build-smoke (#884)",
      "workflow": "Build and deploy Zola site to GitHub Pages",
      "branch": "main",
      "sha": "7b96ef1",
      "event": "push",
      "status": "in_progress",
      "conclusion": "",
      "created_at": "2026-06-25T00:54:59Z",
      "updated_at": "2026-06-25T00:55:04Z",
      "url": "https://github.com/Banhang-Chogao/zola/actions/runs/28139565154"
    },
    {
      "id": 28139565153,
      "title": "fix(links): clear 10 internal 404s for green build-smoke (#884)",
      "workflow": "Blog Heart Beat",
      "branch": "main",
      "sha": "7b96ef1",
      "event": "push",
      "status": "in_progress",
      "conclusion": "",
      "created_at": "2026-06-25T00:54:59Z",
      "updated_at": "2026-06-25T00:55:03Z",
      "url": "https://github.com/Banhang-Chogao/zola/actions/runs/28139565153"
    },
    {
      "id": 28139565143,
      "title": "fix(links): clear 10 internal 404s for green build-smoke (#884)",
      "workflow": "IndexNow ping",
      "branch": "main",
      "sha": "7b96ef1",
      "event": "push",
      "status": "in_progress",
      "conclusion": "",
      "created_at": "2026-06-25T00:54:59Z",
      "updated_at": "2026-06-25T00:55:03Z",
      "url": "https://github.com/Banhang-Chogao/zola/actions/runs/28139565143"
    },
    {
      "id": 28139565141,
      "title": "fix(links): clear 10 internal 404s for green build-smoke (#884)",
      "workflow": "Build Semantic Related Posts",
      "branch": "main",
      "sha": "7b96ef1",
      "event": "push",
      "status": "in_progress",
      "conclusion": "",
      "created_at": "2026-06-25T00:54:59Z",
      "updated_at": "2026-06-25T00:55:04Z",
      "url": "https://github.com/Banhang-Chogao/zola/actions/runs/28139565141"
    },
    {
      "id": 28139565140,
      "title": "fix(links): clear 10 internal 404s for green build-smoke (#884)",
      "workflow": "QA Gatekeeper",
      "branch": "main",
      "sha": "7b96ef1",
      "event": "push",
      "status": "in_progress",
      "conclusion": "",
      "created_at": "2026-06-25T00:54:59Z",
      "updated_at": "2026-06-25T00:55:03Z",
      "url": "https://github.com/Banhang-Chogao/zola/actions/runs/28139565140"
    },
    {
      "id": 28139560112,
      "title": "QA Rule Checker",
      "workflow": "QA Rule Checker",
      "branch": "main",
      "sha": "347f9e7",
      "event": "workflow_run",
      "status": "completed",
      "conclusion": "skipped",
      "created_at": "2026-06-25T00:54:50Z",
      "updated_at": "2026-06-25T00:54:51Z",
      "url": "https://github.com/Banhang-Chogao/zola/actions/runs/28139560112"
    },
    {
      "id": 28139560111,
      "title": "Auto-merge",
      "workflow": "Auto-merge",
      "branch": "main",
      "sha": "347f9e7",
      "event": "workflow_run",
      "status": "completed",
      "conclusion": "success",
      "created_at": "2026-06-25T00:54:50Z",
      "updated_at": "2026-06-25T00:55:02Z",
      "url": "https://github.com/Banhang-Chogao/zola/actions/runs/28139560111"
    },
    {
      "id": 28139468000,
      "title": "QA Rule Checker",
      "workflow": "QA Rule Checker",
      "branch": "main",
      "sha": "cfea8b4",
      "event": "workflow_run",
      "status": "completed",
      "conclusion": "success",
      "created_at": "2026-06-25T00:52:14Z",
      "updated_at": "2026-06-25T00:52:28Z",
      "url": "https://github.com/Banhang-Chogao/zola/actions/runs/28139468000"
    },
    {
      "id": 28139459309,
      "title": "Sitemap Submit",
      "workflow": "Sitemap Submit",
      "branch": "main",
      "sha": "cfea8b4",
      "event": "workflow_run",
      "status": "completed",
      "conclusion": "success",
      "created_at": "2026-06-25T00:52:00Z",
      "updated_at": "2026-06-25T00:52:13Z",
      "url": "https://github.com/Banhang-Chogao/zola/actions/runs/28139459309"
    },
    {
      "id": 28139459305,
      "title": "Compliance Score Audit",
      "workflow": "Compliance Score Audit",
      "branch": "main",
      "sha": "cfea8b4",
      "event": "workflow_run",
      "status": "completed",
      "conclusion": "failure",
      "created_at": "2026-06-25T00:52:00Z",
      "updated_at": "2026-06-25T00:52:11Z",
      "url": "https://github.com/Banhang-Chogao/zola/actions/runs/28139459305"
    },
    {
      "id": 28139459224,
      "title": "QA Rule Checker",
      "workflow": "QA Rule Checker",
      "branch": "main",
      "sha": "cfea8b4",
      "event": "workflow_run",
      "status": "completed",
      "conclusion": "skipped",
      "created_at": "2026-06-25T00:52:00Z",
      "updated_at": "2026-06-25T00:52:07Z",
      "url": "https://github.com/Banhang-Chogao/zola/actions/runs/28139459224"
    },
    {
      "id": 28139363020,
      "title": "fix(links): clear 10 internal 404s for green build-smoke [fix/go-live-404-links]",
      "workflow": "Merge Conflict Preflight",
      "branch": "fix/go-live-404-links",
      "sha": "0508ebc",
      "event": "pull_request",
      "status": "completed",
      "conclusion": "success",
      "created_at": "2026-06-25T00:49:24Z",
      "updated_at": "2026-06-25T00:49:36Z",
      "url": "https://github.com/Banhang-Chogao/zola/actions/runs/28139363020"
    },
    {
      "id": 28139359084,
      "title": "fix(links): clear 10 internal 404s for green build-smoke",
      "workflow": "Auto PR Gatekeeper",
      "branch": "fix/go-live-404-links",
      "sha": "0508ebc",
      "event": "push",
      "status": "completed",
      "conclusion": "success",
      "created_at": "2026-06-25T00:49:18Z",
      "updated_at": "2026-06-25T00:49:29Z",
      "url": "https://github.com/Banhang-Chogao/zola/actions/runs/28139359084"
    },
    {
      "id": 28139359076,
      "title": "fix(links): clear 10 internal 404s for green build-smoke",
      "workflow": "QA Gatekeeper",
      "branch": "fix/go-live-404-links",
      "sha": "0508ebc",
      "event": "push",
      "status": "completed",
      "conclusion": "success",
      "created_at": "2026-06-25T00:49:18Z",
      "updated_at": "2026-06-25T00:54:47Z",
      "url": "https://github.com/Banhang-Chogao/zola/actions/runs/28139359076"
    },
    {
      "id": 28139359075,
      "title": "fix(links): clear 10 internal 404s for green build-smoke",
      "workflow": "Slack Commit Notification",
      "branch": "fix/go-live-404-links",
      "sha": "0508ebc",
      "event": "push",
      "status": "completed",
      "conclusion": "success",
      "created_at": "2026-06-25T00:49:18Z",
      "updated_at": "2026-06-25T00:49:24Z",
      "url": "https://github.com/Banhang-Chogao/zola/actions/runs/28139359075"
    },
    {
      "id": 28139229670,
      "title": "IndexNow ping",
      "workflow": "IndexNow ping",
      "branch": "main",
      "sha": "cfea8b4",
      "event": "workflow_dispatch",
      "status": "completed",
      "conclusion": "success",
      "created_at": "2026-06-25T00:45:34Z",
      "updated_at": "2026-06-25T00:45:47Z",
      "url": "https://github.com/Banhang-Chogao/zola/actions/runs/28139229670"
    },
    {
      "id": 28139228690,
      "title": "Sitemap Submit",
      "workflow": "Sitemap Submit",
      "branch": "main",
      "sha": "cfea8b4",
      "event": "workflow_dispatch",
      "status": "completed",
      "conclusion": "success",
      "created_at": "2026-06-25T00:45:32Z",
      "updated_at": "2026-06-25T00:45:44Z",
      "url": "https://github.com/Banhang-Chogao/zola/actions/runs/28139228690"
    },
    {
      "id": 28139227501,
      "title": "Build and deploy Zola site to GitHub Pages",
      "workflow": "Build and deploy Zola site to GitHub Pages",
      "branch": "main",
      "sha": "cfea8b4",
      "event": "workflow_dispatch",
      "status": "completed",
      "conclusion": "success",
      "created_at": "2026-06-25T00:45:30Z",
      "updated_at": "2026-06-25T00:51:58Z",
      "url": "https://github.com/Banhang-Chogao/zola/actions/runs/28139227501"
    },
    {
      "id": 28138886954,
      "title": "QA Rule Checker",
      "workflow": "QA Rule Checker",
      "branch": "main",
      "sha": "4c81182",
      "event": "workflow_run",
      "status": "completed",
      "conclusion": "success",
      "created_at": "2026-06-25T00:36:09Z",
      "updated_at": "2026-06-25T00:36:19Z",
      "url": "https://github.com/Banhang-Chogao/zola/actions/runs/28138886954"
    },
    {
      "id": 28138880104,
      "title": "QA Rule Checker",
      "workflow": "QA Rule Checker",
      "branch": "main",
      "sha": "4c81182",
      "event": "workflow_run",
      "status": "completed",
      "conclusion": "skipped",
      "created_at": "2026-06-25T00:35:57Z",
      "updated_at": "2026-06-25T00:36:08Z",
      "url": "https://github.com/Banhang-Chogao/zola/actions/runs/28138880104"
    },
    {
      "id": 28138880055,
      "title": "Compliance Score Audit",
      "workflow": "Compliance Score Audit",
      "branch": "main",
      "sha": "4c81182",
      "event": "workflow_run",
      "status": "completed",
      "conclusion": "failure",
      "created_at": "2026-06-25T00:35:57Z",
      "updated_at": "2026-06-25T00:36:07Z",
      "url": "https://github.com/Banhang-Chogao/zola/actions/runs/28138880055"
    },
    {
      "id": 28138880045,
      "title": "Sitemap Submit",
      "workflow": "Sitemap Submit",
      "branch": "main",
      "sha": "4c81182",
      "event": "workflow_run",
      "status": "completed",
      "conclusion": "success",
      "created_at": "2026-06-25T00:35:57Z",
      "updated_at": "2026-06-25T00:36:09Z",
      "url": "https://github.com/Banhang-Chogao/zola/actions/runs/28138880045"
    },
    {
      "id": 28138849084,
      "title": "QA Rule Checker",
      "workflow": "QA Rule Checker",
      "branch": "main",
      "sha": "11759d4",
      "event": "workflow_run",
      "status": "completed",
      "conclusion": "success",
      "created_at": "2026-06-25T00:35:05Z",
      "updated_at": "2026-06-25T00:35:17Z",
      "url": "https://github.com/Banhang-Chogao/zola/actions/runs/28138849084"
    },
    {
      "id": 28138849069,
      "title": "Auto-merge",
      "workflow": "Auto-merge",
      "branch": "main",
      "sha": "11759d4",
      "event": "workflow_run",
      "status": "completed",
      "conclusion": "skipped",
      "created_at": "2026-06-25T00:35:05Z",
      "updated_at": "2026-06-25T00:35:07Z",
      "url": "https://github.com/Banhang-Chogao/zola/actions/runs/28138849069"
    },
    {
      "id": 28138670988,
      "title": "QA Rule Checker",
      "workflow": "QA Rule Checker",
      "branch": "main",
      "sha": "bce923d",
      "event": "workflow_run",
      "status": "completed",
      "conclusion": "success",
      "created_at": "2026-06-25T00:30:18Z",
      "updated_at": "2026-06-25T00:30:28Z",
      "url": "https://github.com/Banhang-Chogao/zola/actions/runs/28138670988"
    },
    {
      "id": 28138661352,
      "title": "Compliance Score Audit",
      "workflow": "Compliance Score Audit",
      "branch": "main",
      "sha": "9b2f158",
      "event": "workflow_run",
      "status": "completed",
      "conclusion": "failure",
      "created_at": "2026-06-25T00:30:04Z",
      "updated_at": "2026-06-25T00:30:16Z",
      "url": "https://github.com/Banhang-Chogao/zola/actions/runs/28138661352"
    },
    {
      "id": 28138661314,
      "title": "Sitemap Submit",
      "workflow": "Sitemap Submit",
      "branch": "main",
      "sha": "9b2f158",
      "event": "workflow_run",
      "status": "completed",
      "conclusion": "skipped",
      "created_at": "2026-06-25T00:30:04Z",
      "updated_at": "2026-06-25T00:30:05Z",
      "url": "https://github.com/Banhang-Chogao/zola/actions/runs/28138661314"
    },
    {
      "id": 28138661301,
      "title": "QA Rule Checker",
      "workflow": "QA Rule Checker",
      "branch": "main",
      "sha": "9b2f158",
      "event": "workflow_run",
      "status": "completed",
      "conclusion": "success",
      "created_at": "2026-06-25T00:30:04Z",
      "updated_at": "2026-06-25T00:30:15Z",
      "url": "https://github.com/Banhang-Chogao/zola/actions/runs/28138661301"
    },
    {
      "id": 28138641392,
      "title": "fix(theme): CI submodule checkout + Linkita page.html with TOC rail (…",
      "workflow": "Slack Commit Notification",
      "branch": "main",
      "sha": "6457455",
      "event": "push",
      "status": "completed",
      "conclusion": "success",
      "created_at": "2026-06-25T00:29:30Z",
      "updated_at": "2026-06-25T00:29:39Z",
      "url": "https://github.com/Banhang-Chogao/zola/actions/runs/28138641392"
    }
  ],
  "deploy_runs": [
    {
      "id": 28139565154,
      "title": "fix(links): clear 10 internal 404s for green build-smoke (#884)",
      "workflow": "Build and deploy Zola site to GitHub Pages",
      "branch": "main",
      "sha": "7b96ef1",
      "event": "push",
      "status": "in_progress",
      "conclusion": "",
      "created_at": "2026-06-25T00:54:59Z",
      "updated_at": "2026-06-25T00:55:04Z",
      "url": "https://github.com/Banhang-Chogao/zola/actions/runs/28139565154"
    },
    {
      "id": 28139227501,
      "title": "Build and deploy Zola site to GitHub Pages",
      "workflow": "Build and deploy Zola site to GitHub Pages",
      "branch": "main",
      "sha": "cfea8b4",
      "event": "workflow_dispatch",
      "status": "completed",
      "conclusion": "success",
      "created_at": "2026-06-25T00:45:30Z",
      "updated_at": "2026-06-25T00:51:58Z",
      "url": "https://github.com/Banhang-Chogao/zola/actions/runs/28139227501"
    },
    {
      "id": 28138641329,
      "title": "fix(theme): CI submodule checkout + Linkita page.html with TOC rail (…",
      "workflow": "Build and deploy Zola site to GitHub Pages",
      "branch": "main",
      "sha": "6457455",
      "event": "push",
      "status": "completed",
      "conclusion": "success",
      "created_at": "2026-06-25T00:29:30Z",
      "updated_at": "2026-06-25T00:35:54Z",
      "url": "https://github.com/Banhang-Chogao/zola/actions/runs/28138641329"
    },
    {
      "id": 28138023014,
      "title": "fix(ci): remove cache:'npm' from qa.yml and deploy.yml [fix/ci-remove…",
      "workflow": "Build and deploy Zola site to GitHub Pages",
      "branch": "main",
      "sha": "7abf249",
      "event": "push",
      "status": "completed",
      "conclusion": "failure",
      "created_at": "2026-06-25T00:13:00Z",
      "updated_at": "2026-06-25T00:30:02Z",
      "url": "https://github.com/Banhang-Chogao/zola/actions/runs/28138023014"
    },
    {
      "id": 28137964960,
      "title": "feat(theme): install Linkita v4 and force theme for core blog pages […",
      "workflow": "Build and deploy Zola site to GitHub Pages",
      "branch": "main",
      "sha": "c0de971",
      "event": "push",
      "status": "completed",
      "conclusion": "cancelled",
      "created_at": "2026-06-25T00:11:28Z",
      "updated_at": "2026-06-25T00:13:01Z",
      "url": "https://github.com/Banhang-Chogao/zola/actions/runs/28137964960"
    },
    {
      "id": 28137714141,
      "title": "hotfix: disable Cloudflare R2 connection [hotfix/disable-r2] (#881)",
      "workflow": "Build and deploy Zola site to GitHub Pages",
      "branch": "main",
      "sha": "870e4c0",
      "event": "push",
      "status": "completed",
      "conclusion": "cancelled",
      "created_at": "2026-06-25T00:05:07Z",
      "updated_at": "2026-06-25T00:11:30Z",
      "url": "https://github.com/Banhang-Chogao/zola/actions/runs/28137714141"
    },
    {
      "id": 28136833512,
      "title": "fix(wwdc26): render branding and catalogue via block main",
      "workflow": "Build and deploy Zola site to GitHub Pages",
      "branch": "main",
      "sha": "dd4a63a",
      "event": "push",
      "status": "completed",
      "conclusion": "failure",
      "created_at": "2026-06-24T23:42:51Z",
      "updated_at": "2026-06-25T00:24:20Z",
      "url": "https://github.com/Banhang-Chogao/zola/actions/runs/28136833512"
    },
    {
      "id": 28135518635,
      "title": "fix(build): remove index-backup.html from templates — Zola parses all…",
      "workflow": "Build and deploy Zola site to GitHub Pages",
      "branch": "main",
      "sha": "3199435",
      "event": "push",
      "status": "completed",
      "conclusion": "failure",
      "created_at": "2026-06-24T23:09:55Z",
      "updated_at": "2026-06-25T00:00:55Z",
      "url": "https://github.com/Banhang-Chogao/zola/actions/runs/28135518635"
    },
    {
      "id": 28132821806,
      "title": "fix: WWDC26 homepage — load posting+baochi posts, full-width layout, …",
      "workflow": "Build and deploy Zola site to GitHub Pages",
      "branch": "main",
      "sha": "16952e2",
      "event": "push",
      "status": "completed",
      "conclusion": "failure",
      "created_at": "2026-06-24T22:09:06Z",
      "updated_at": "2026-06-24T22:40:50Z",
      "url": "https://github.com/Banhang-Chogao/zola/actions/runs/28132821806"
    },
    {
      "id": 28132505168,
      "title": "feat: redesign homepage WWDC26 style (override index.html)",
      "workflow": "Build and deploy Zola site to GitHub Pages",
      "branch": "main",
      "sha": "598b0db",
      "event": "push",
      "status": "completed",
      "conclusion": "cancelled",
      "created_at": "2026-06-24T22:02:37Z",
      "updated_at": "2026-06-24T22:09:07Z",
      "url": "https://github.com/Banhang-Chogao/zola/actions/runs/28132505168"
    }
  ]
}
